apkdownloader/__init__.py
apkdownloader/config.py
apkdownloader/googleplay.py
apkdownloader/googleplay_pb2.py
apkdownloader/utils.py
apkdownloader-0.0.4.dist-info/METADATA
apkdownloader-0.0.4.dist-info/WHEEL
apkdownloader-0.0.4.dist-info/top_level.txt
apkdownloader-0.0.4.dist-info/RECORD
