Metadata-Version: 2.1
Name: apkdownloader
Version: 0.0.4
Summary: Download apk from Google Play via package name.
Home-page: https://github.com/krnick/apk-downloader
Author: SONG,JUN-WEI
Author-email: sungboss2004@gmail.com
License: MIT Licence
Keywords: apk,apk download,download apk
Platform: UNKNOWN
Classifier: Programming Language :: Python :: 3
Classifier: License :: OSI Approved :: MIT License
Classifier: Operating System :: OS Independent
Requires-Dist: cryptography
Requires-Dist: requests
Requires-Dist: protobuf
